pykotokenizer/.DS_Store
pykotokenizer/__init__.py
pykotokenizer/ko_hannanum.py
pykotokenizer/ko_kkma.py
pykotokenizer/ko_komoran.py
pykotokenizer/ko_spacing.py
pykotokenizer/ko_tokenizer.py
pykotokenizer/resources/.DS_Store
pykotokenizer/resources/ko_spacing/.DS_Store
pykotokenizer/resources/ko_spacing/dicts/c2v.dic
pykotokenizer/resources/ko_spacing/models/ko_spacing_model
pykotokenizer/resources/ko_tokenizer/data/word2idx0.json
pykotokenizer/resources/ko_tokenizer/models/model_th7.hdf5
tests/__init__.py
pykotokenizer-0.0.3.dist-info/LICENSE
pykotokenizer-0.0.3.dist-info/METADATA
pykotokenizer-0.0.3.dist-info/WHEEL
pykotokenizer-0.0.3.dist-info/top_level.txt
pykotokenizer-0.0.3.dist-info/RECORD
