Metadata-Version: 2.1
Name: pykotokenizer
Version: 0.0.3
Summary: Model-based Korean Text Tokenizer in Python
Home-page: https://github.com/abdalimran/pykotokenizer
Author: Abdullah Al Imran
Author-email: abdalimran@gmail.com
License: UNKNOWN
Project-URL: Bug Tracker, https://github.com/pypa/pykotokenizer/issues
Platform: UNKNOWN
Classifier: Programming Language :: Python :: 3
Classifier: License :: OSI Approved :: MIT License
Classifier: Operating System :: OS Independent
Requires-Python: <3.9,>=3.6
License-File: LICENSE
